CHANGELOG.md
LICENSE.txt
MANIFEST.in
README.md
out.txt
setup.py
adofaipy/__init__.py
adofaipy/out.txt
adofaipy.egg-info/PKG-INFO
adofaipy.egg-info/SOURCES.txt
adofaipy.egg-info/dependency_links.txt
adofaipy.egg-info/top_level.txt