Metadata-Version: 2.1
Name: adofaipy
Version: 3.2.1
Summary: A library that makes automating events in ADOFAI levels more convenient.
Home-page: https://github.com/M1n3c4rt/adofaipy
Author: M1n3c4rt
Author-email: vedicbits@gmail.com
License: MIT
Keywords: adofai
Classifier: Development Status :: 5 - Production/Stable
Classifier: Intended Audience :: Developers
Classifier: Operating System :: Microsoft :: Windows :: Windows 10
Classifier: License :: OSI Approved :: MIT License
Classifier: Programming Language :: Python :: 3.11
License-File: LICENSE.txt
